{
  "_version": "3.0",
  "_lastUpdate": "2026-02-19",
  "_comment": "BottomUP Martingale V2 — Kripto + Hisse + Emtia",

  "defaults": {
    "symbol": "ETHUSDT",
    "timeframe": "1h",
    "market": "crypto",
    "initialCapital": 10000,
    "useManual": true,
    "useEma": true,
    "emaLength": 10,
    "useRsi": false,
    "rsiLevel": 71,
    "atrLength": 14,
    "profitDivisor": 2
  },

  "allocations": {
    "layer1": 10, "layer2": 15, "layer3": 20, "layer4": 25, "layer5": 30
  },

  "markets": {
    "crypto": {
      "label": "🪙 Kripto",
      "source": "binance",
      "symbols": [
        "BTCUSDT","ETHUSDT","SOLUSDT","BNBUSDT","XRPUSDT","DOGEUSDT","ADAUSDT",
        "AVAXUSDT","DOTUSDT","LINKUSDT","MATICUSDT","UNIUSDT","ATOMUSDT",
        "NEARUSDT","LTCUSDT","APTUSDT","ARBUSDT","OPUSDT","SUIUSDT","SEIUSDT",
        "INJUSDT","TIAUSDT","TONUSDT","PEPEUSDT","WIFUSDT","TRXUSDT"
      ],
      "timeframes": [
        {"label":"15m","value":"15m","limit":500},
        {"label":"1h","value":"1h","limit":500},
        {"label":"4h","value":"4h","limit":500},
        {"label":"1d","value":"1d","limit":365},
        {"label":"1w","value":"1w","limit":200}
      ]
    },
    "stocks": {
      "label": "📈 ABD Hisse",
      "source": "yahoo",
      "symbols": [
        "AAPL","MSFT","GOOGL","AMZN","NVDA","META","TSLA","BRK-B",
        "JPM","V","UNH","MA","HD","PG","JNJ","XOM","COST","ABBV",
        "MRK","AVGO","KO","PEP","WMT","LLY","NFLX","AMD","CRM",
        "ORCL","DIS","ADBE","CSCO","INTC","QCOM","BA","NKE",
        "PYPL","SQ","COIN","PLTR","SOFI","RIVN","SNOW","UBER"
      ],
      "timeframes": [
        {"label":"1g","value":"1d","range":"6mo"},
        {"label":"1h","value":"1h","range":"5d"},
        {"label":"5d","value":"5d","range":"1y"},
        {"label":"1a","value":"1wk","range":"2y"},
        {"label":"1ay","value":"1mo","range":"10y"}
      ]
    },
    "commodities": {
      "label": "🏗️ Emtia",
      "source": "yahoo",
      "symbols": [
        "GC=F","SI=F","CL=F","NG=F","HG=F","PL=F","PA=F",
        "ZC=F","ZW=F","ZS=F","KC=F","CC=F","SB=F","CT=F",
        "ALI=F","EURUSD=X","GBPUSD=X","USDJPY=X","USDTRY=X"
      ],
      "displayNames": {
        "GC=F":"Altın","SI=F":"Gümüş","CL=F":"Petrol (WTI)","NG=F":"Doğalgaz",
        "HG=F":"Bakır","PL=F":"Platin","PA=F":"Paladyum",
        "ZC=F":"Mısır","ZW=F":"Buğday","ZS=F":"Soya","KC=F":"Kahve",
        "CC=F":"Kakao","SB=F":"Şeker","CT=F":"Pamuk","ALI=F":"Alüminyum",
        "EURUSD=X":"EUR/USD","GBPUSD=X":"GBP/USD","USDJPY=X":"USD/JPY","USDTRY=X":"USD/TRY"
      },
      "timeframes": [
        {"label":"1g","value":"1d","range":"6mo"},
        {"label":"1h","value":"1h","range":"5d"},
        {"label":"5d","value":"5d","range":"1y"},
        {"label":"1a","value":"1wk","range":"2y"},
        {"label":"1ay","value":"1mo","range":"10y"}
      ]
    }
  },

  "smartDefaults": {
    "BTC":    {"aptr":[200,500,1500,3000,6000],"profit":[100,250,750,1500,3000]},
    "ETH":    {"aptr":[10,30,80,200,500],"profit":[5,15,40,100,250]},
    "BNB":    {"aptr":[3,8,20,50,100],"profit":[1.5,4,10,25,50]},
    "MID":    {"aptr":[0.5,2,5,15,30],"profit":[0.25,1,2.5,7,15]},
    "LOW":    {"aptr":[0.002,0.005,0.015,0.04,0.1],"profit":[0.001,0.0025,0.007,0.02,0.05]},
    "STOCK":  {"aptr":[1,3,8,20,50],"profit":[0.5,1.5,4,10,25]},
    "COMMODITY":{"aptr":[2,5,15,40,100],"profit":[1,2.5,7,20,50]},
    "OTHER":  {"aptr":[1,3,10,25,60],"profit":[0.5,1.5,5,12,30]}
  },

  "symbolGroups": {
    "MID": ["SOLUSDT","AVAXUSDT","DOTUSDT","LINKUSDT","UNIUSDT","NEARUSDT","APTUSDT","INJUSDT","SUIUSDT","ATOMUSDT"],
    "LOW": ["DOGEUSDT","PEPEUSDT","WIFUSDT","SEIUSDT","TRXUSDT","XRPUSDT","ADAUSDT"]
  },

  "riskRules": {
    "viable":{"returnMin":0,"maxDDMax":25,"profitFactorMin":1.2},
    "risky":{"returnMin":0},
    "unprofitable":{"returnMax":0}
  }
}
